MANIFEST.in
README.rst
setup.py
bigsudo/__init__.py
bigsudo/bootstrap.yml
bigsudo/console_script.py
bigsudo/role-all.yml
bigsudo/tasks.yml
bigsudo.egg-info/PKG-INFO
bigsudo.egg-info/SOURCES.txt
bigsudo.egg-info/dependency_links.txt
bigsudo.egg-info/entry_points.txt
bigsudo.egg-info/requires.txt
bigsudo.egg-info/top_level.txt
bigsudo/callback_plugins/unixy.py