Metadata-Version: 2.4
Name: bigsudo
Version: 1.1.1
Summary: Obscene ansible runner
Home-page: https://yourlabs.io/oss/bigsudo
Keywords: automation cli ansible
Requires-Python: >=3
Requires-Dist: cli2>=2.2
Requires-Dist: requests
Dynamic: description
Dynamic: description-content-type
Dynamic: home-page
Dynamic: keywords
Dynamic: requires-dist
Dynamic: requires-python
Dynamic: summary
